LICENSE
MANIFEST.in
README.md
requirements.txt
setup.py
scrapy_tor_downloader.egg-info/PKG-INFO
scrapy_tor_downloader.egg-info/SOURCES.txt
scrapy_tor_downloader.egg-info/dependency_links.txt
scrapy_tor_downloader.egg-info/not-zip-safe
scrapy_tor_downloader.egg-info/requires.txt
scrapy_tor_downloader.egg-info/top_level.txt
tormiddleware/__init__.py
tormiddleware/middleware.py
tormiddleware/response.py