Metadata-Version: 2.1
Name: scrapy-tor-downloader
Version: 1.0.4
Summary: Scrapy middleware with TOR support for more robust scrapers or anonymous scraping.
Home-page: https://github.com/8W9aG/scrapy-tor-downloader
Author: Will Sackfield
Author-email: will.sackfield@gmail.com
License: MIT
Keywords: scrapy middleware tor
Platform: UNKNOWN
Classifier: License :: OSI Approved :: MIT License
Classifier: Programming Language :: Python :: 3
Classifier: Framework :: Scrapy
License-File: LICENSE
